sentok/__init__.py
sentok/main.py
sentok/sentok_weights.py
tests/__init__.py
tests/test_main.py
sentok-0.1.2.dist-info/LICENSE
sentok-0.1.2.dist-info/METADATA
sentok-0.1.2.dist-info/WHEEL
sentok-0.1.2.dist-info/top_level.txt
sentok-0.1.2.dist-info/RECORD
