Metadata-Version: 2.1
Name: sentok
Version: 0.1.2
Summary: A fast and dynamic python package for converting paragraphs into sentences with customizable thresholds for adaptive sentence segmentation.
Home-page: https://github.com/kothiyarajesh/sentok
Author: Rajesh Kothiya
Author-email: rkahir2222@gmail.com
License: MIT
Project-URL: Homepage, https://github.com/kothiyarajesh/sentok
Project-URL: Bug Reports, https://github.com/kothiyarajesh/sentok/issues
Project-URL: Source, https://github.com/kothiyarajesh/sentok
Keywords: sentence tokenization,natural language processing,text segmentation
Classifier: Programming Language :: Python :: 3
Classifier: Programming Language :: Python :: 3.9
Classifier: Programming Language :: Python :: 3.10
Classifier: License :: OSI Approved :: MIT License
Classifier: Operating System :: OS Independent
Requires-Python: >=3.9
License-File: LICENSE
Requires-Dist: numpy
Requires-Dist: pandas
Provides-Extra: dev
Requires-Dist: pytest ; extra == 'dev'
Requires-Dist: black ; extra == 'dev'
Requires-Dist: flake8 ; extra == 'dev'
